LICENSE
MANIFEST.in
README.md
setup.py
potsdb/__init__.py
potsdb/client.py
potsdb.egg-info/PKG-INFO
potsdb.egg-info/SOURCES.txt
potsdb.egg-info/dependency_links.txt
potsdb.egg-info/top_level.txt
potsdb/tests/__init__.py
potsdb/tests/test_potsdb.py