Metadata-Version: 1.1
Name: potsdb
Version: 1.0.3
Summary: A Python client for OpenTSDB which creates a separate thread for TCP communication.
Home-page: http://github.com/orionvm/potsdb
Author: Alex Sharp, Chris McClymont
Author-email: alex.sharp@orionvm.com
License: GNU GPL
Keywords: opentsdb,tsdb,time series
Platform: UNKNOWN
Classifier: Development Status :: 5 - Production/Stable
Classifier: Intended Audience :: Developers
Classifier: Intended Audience :: System Administrators
Classifier: Operating System :: Unix
Classifier: Topic :: Utilities
